repo2rocrate/__init__.py
repo2rocrate/cli.py
repo2rocrate/common.py
repo2rocrate/galaxy.py
repo2rocrate/nextflow.py
repo2rocrate/snakemake.py
repo2rocrate/utils.py
repo2rocrate/version.py
repo2rocrate-0.1.1.dist-info/LICENSE
repo2rocrate-0.1.1.dist-info/METADATA
repo2rocrate-0.1.1.dist-info/WHEEL
repo2rocrate-0.1.1.dist-info/entry_points.txt
repo2rocrate-0.1.1.dist-info/top_level.txt
repo2rocrate-0.1.1.dist-info/zip-safe
repo2rocrate-0.1.1.dist-info/RECORD
