Metadata-Version: 2.1
Name: repo2rocrate
Version: 0.1.1
Summary: Generate RO-Crates from workflow repositories
Home-page: https://github.com/crs4/repo2rocrate
Author: Simone Leo
Author-email: <simone.leo@crs4.it>
License: Apache-2.0
Platform: Linux
Classifier: Programming Language :: Python :: 3
Classifier: License :: OSI Approved :: Apache Software License
Classifier: Operating System :: OS Independent
Classifier: Topic :: Scientific/Engineering
Classifier: Intended Audience :: Science/Research
Requires-Python: >=3.6, <4
License-File: LICENSE
Requires-Dist: click
Requires-Dist: pyyaml
Requires-Dist: rocrate
